cloudflare_request_cert/__init__.py
cloudflare_request_cert/main.py
cloudflare_request_cert-0.1.3.dist-info/METADATA
cloudflare_request_cert-0.1.3.dist-info/WHEEL
cloudflare_request_cert-0.1.3.dist-info/entry_points.txt
cloudflare_request_cert-0.1.3.dist-info/licenses/LICENSE
cloudflare_request_cert-0.1.3.dist-info/RECORD
