Metadata-Version: 2.4
Name: cloudflare-request-cert
Version: 0.1.3
Summary: SSL/TLS certificate automation using Cloudflare DNS
Project-URL: Homepage, https://github.com/hellqvio86/cloudflare-request-cert
Project-URL: Repository, https://github.com/hellqvio86/cloudflare-request-cert
Project-URL: Issues, https://github.com/hellqvio86/cloudflare-request-cert/issues
Author-email: Olof Hellqvist <olof.hellqvist@gmail.com>
License: MIT
License-File: LICENSE
Keywords: certbot,cloudflare,dns-01,ssl,tls
Classifier: Development Status :: 4 - Beta
Classifier: Intended Audience :: System Administrators
Classifier: License :: OSI Approved :: MIT License
Classifier: Programming Language :: Python :: 3
Classifier: Programming Language :: Python :: 3.10
Classifier: Programming Language :: Python :: 3.11
Classifier: Programming Language :: Python :: 3.12
Classifier: Programming Language :: Python :: 3.13
Classifier: Programming Language :: Python :: 3.14
Classifier: Topic :: Security
Classifier: Topic :: System :: Systems Administration
Requires-Python: >=3.10
Requires-Dist: certbot-dns-cloudflare>=2.11.0
Requires-Dist: certbot>=2.11.0
Provides-Extra: dev
Requires-Dist: cyclonedx-bom>=5.0.0; extra == 'dev'
Requires-Dist: pytest-cov>=6.0.0; extra == 'dev'
Requires-Dist: pytest-mock>=3.10.0; extra == 'dev'
Requires-Dist: pytest>=8.3.0; extra == 'dev'
Requires-Dist: ruff>=0.8.0; extra == 'dev'
